oidc_auth/__init__.py
oidc_auth/authentication.py
oidc_auth/settings.py
oidc_auth/test.py
oidc_auth/util.py
drf_oidc_auth-3.0.0.dist-info/LICENSE
drf_oidc_auth-3.0.0.dist-info/METADATA
drf_oidc_auth-3.0.0.dist-info/WHEEL
drf_oidc_auth-3.0.0.dist-info/top_level.txt
drf_oidc_auth-3.0.0.dist-info/RECORD
